streamable/__init__.py
streamable/_aiterators.py
streamable/_iterators.py
streamable/afunctions.py
streamable/functions.py
streamable/py.typed
streamable/stream.py
streamable/_util/__init__.py
streamable/_util/_asynctools.py
streamable/_util/_constants.py
streamable/_util/_contextmanagertools.py
streamable/_util/_errortools.py
streamable/_util/_functiontools.py
streamable/_util/_futuretools.py
streamable/_util/_iterabletools.py
streamable/_util/_loggertools.py
streamable/_util/_protocols.py
streamable/_util/_validationtools.py
streamable/visitors/__init__.py
streamable/visitors/_aiterator.py
streamable/visitors/_base.py
streamable/visitors/_equality.py
streamable/visitors/_iterator.py
streamable/visitors/_representation.py
streamable-1.6.6.dist-info/licenses/LICENSE
streamable-1.6.6.dist-info/METADATA
streamable-1.6.6.dist-info/WHEEL
streamable-1.6.6.dist-info/top_level.txt
streamable-1.6.6.dist-info/RECORD
