Metadata-Version: 2.4
Name: streamable
Version: 1.6.6
Summary: concurrent & fluent interface for (async) iterables
Home-page: https://github.com/ebonnal/streamable
Author: ebonnal
Author-email: bonnal.enzo.dev@gmail.com
License: Apache 2.
License-File: LICENSE
Dynamic: author
Dynamic: author-email
Dynamic: description
Dynamic: description-content-type
Dynamic: home-page
Dynamic: license
Dynamic: license-file
Dynamic: summary
